LICENSE
MANIFEST.in
README.md
package.json
pyproject.toml
setup.py
tsconfig.json
gquantlab/__init__.py
gquantlab/_frontend.py
gquantlab/_version.py
gquantlab/gquantmodel.py
gquantlab/handlers.py
gquantlab/server_utils.py
gquantlab.egg-info/PKG-INFO
gquantlab.egg-info/SOURCES.txt
gquantlab.egg-info/dependency_links.txt
gquantlab.egg-info/not-zip-safe
gquantlab.egg-info/requires.txt
gquantlab.egg-info/top_level.txt
gquantlab/labextension/package.json
gquantlab/labextension/static/216.592ebc5b1ffa92cfdfcf.js
gquantlab/labextension/static/216.592ebc5b1ffa92cfdfcf.js.LICENSE.txt
gquantlab/labextension/static/33.b2fefd747e2b8c08d457.js
gquantlab/labextension/static/33.b2fefd747e2b8c08d457.js.LICENSE.txt
gquantlab/labextension/static/395.9891db223d232743763f.js
gquantlab/labextension/static/44.59449b0c677e032467fa.js
gquantlab/labextension/static/534.7da62172497fc12a8b57.js
gquantlab/labextension/static/534.7da62172497fc12a8b57.js.LICENSE.txt
gquantlab/labextension/static/549.2371c751f0e0829c5fda.js
gquantlab/labextension/static/693.77e73013af43e5a758a9.js
gquantlab/labextension/static/742.e7aa9189e37fab4886d9.js
gquantlab/labextension/static/788.641a33db0c3b30ba1e4b.js
gquantlab/labextension/static/876.8211917e332c34489589.js
gquantlab/labextension/static/901.0cef5e49bec310f8fbeb.js
gquantlab/labextension/static/979.2e86c20acd24b236bc68.js
gquantlab/labextension/static/979.2e86c20acd24b236bc68.js.LICENSE.txt
gquantlab/labextension/static/remoteEntry.21e71461f397fadbad0d.js
gquantlab/labextension/static/style.js
jupyter-config/gquantlab.json
src/EditorPanel.ts
src/FilePathSelector.tsx
src/chart.tsx
src/chartEngine.tsx
src/commands.ts
src/connectionHandler.ts
src/document.ts
src/dragHandler.ts
src/editorWidget.tsx
src/eventHandler.ts
src/gquantlab.ts
src/index.ts
src/mainComponent.tsx
src/nodeEditor.tsx
src/showType.ts
src/svg.d.ts
src/validator.ts
src/version.ts
src/widget.ts
style/clean.svg
style/editor.css
style/gq.svg
style/index.css
style/layout.svg
style/run.svg