Metadata-Version: 2.1
Name: gquantlab
Version: 1.0.0
Summary: gQuant Jupyterlab extension
Home-page: https://github.com/rapidsai/gQuant.git
Author: {'name': 'Yi Dong', 'email': 'doyend@gmail.com'}
License: Apache
Keywords: Jupyter,JupyterLab,JupyterLab3
Platform: Linux
Platform: Mac OS X
Platform: Windows
Classifier: Programming Language :: Python
Classifier: Programming Language :: Python :: 3
Classifier: Programming Language :: Python :: 3.6
Classifier: Programming Language :: Python :: 3.7
Classifier: Programming Language :: Python :: 3.8
Classifier: Framework :: Jupyter
Requires-Python: >=3.6
